msmart/__init__.py
msmart/base_device.py
msmart/cli.py
msmart/cloud.py
msmart/const.py
msmart/crc8.py
msmart/discover.py
msmart/frame.py
msmart/lan.py
msmart/utils.py
msmart/device/__init__.py
msmart/device/AC/__init__.py
msmart/device/AC/command.py
msmart/device/AC/device.py
msmart/device/AC/test_command.py
msmart/device/AC/test_device.py
msmart/device/CC/__init__.py
msmart/device/CC/command.py
msmart/device/CC/device.py
msmart/device/CC/test_command.py
msmart/device/CC/test_device.py
msmart_ng-2025.12.0.dist-info/licenses/LICENSE.md
msmart_ng-2025.12.0.dist-info/METADATA
msmart_ng-2025.12.0.dist-info/WHEEL
msmart_ng-2025.12.0.dist-info/entry_points.txt
msmart_ng-2025.12.0.dist-info/top_level.txt
msmart_ng-2025.12.0.dist-info/RECORD
