Metadata-Version: 2.4
Name: msmart-ng
Version: 2025.12.0
Summary: A Python library for local control of Midea (and associated brands) smart air conditioners.
Author-email: Tucker Kern <tuckkern@gmail.com>
License-Expression: MIT
Project-URL: Repository, https://github.com/mill1000/midea-msmart
Project-URL: Issues, https://github.com/mill1000/midea-msmart/issues
Classifier: Programming Language :: Python :: 3
Classifier: Programming Language :: Python :: 3.9
Classifier: Programming Language :: Python :: 3.10
Classifier: Programming Language :: Python :: 3.11
Classifier: Programming Language :: Python :: 3.12
Classifier: Programming Language :: Python :: 3.13
Classifier: Operating System :: OS Independent
Classifier: Topic :: Home Automation
Requires-Python: >=3.9
License-File: LICENSE.md
Requires-Dist: httpx
Requires-Dist: pycryptodome
Dynamic: license-file
